quasardb_dask/__init__.py
quasardb_dask/client_side.py
quasardb_dask/server_side.py
quasardb_dask-3.14.2.dist-info/METADATA
quasardb_dask-3.14.2.dist-info/WHEEL
quasardb_dask-3.14.2.dist-info/top_level.txt
quasardb_dask-3.14.2.dist-info/RECORD
