Metadata-Version: 2.4
Name: quasardb-dask
Version: 3.14.2
Summary: Integration between QuasarDB's Python API and Dask DataFrame
Author: quasardb SAS
Author-email: contact@quasardb.net
Requires-Python: >=3.11
Requires-Dist: dask[complete]
Requires-Dist: pandas
Requires-Dist: svix-ksuid
Requires-Dist: pendulum
Provides-Extra: python
Requires-Dist: quasardb; extra == "python"
